whats/__init__.py
whats/whats.py
whats-0.1.1.dist-info/DESCRIPTION.rst
whats-0.1.1.dist-info/METADATA
whats-0.1.1.dist-info/RECORD
whats-0.1.1.dist-info/WHEEL
whats-0.1.1.dist-info/entry_points.txt
whats-0.1.1.dist-info/metadata.json
whats-0.1.1.dist-info/top_level.txt
